mempy_miladtsx/__init__.py
mempy_miladtsx/mempy.py
mempy_miladtsx-0.2.2.dist-info/licenses/LICENSE
mempy_miladtsx-0.2.2.dist-info/METADATA
mempy_miladtsx-0.2.2.dist-info/WHEEL
mempy_miladtsx-0.2.2.dist-info/top_level.txt
mempy_miladtsx-0.2.2.dist-info/RECORD
