Metadata-Version: 2.4
Name: mempy_miladtsx
Version: 0.2.2
Summary: A lightweight in-memory store in pure Python
Author-email: TSX <miladtsx@gmail.com>
License-Expression: MIT
Project-URL: Homepage, https://github.com/miladtsx/mempy
Project-URL: Issues, https://github.com/miladtsx/mempy/issues
Keywords: memory,in-memory,store,python
Classifier: Programming Language :: Python :: 3
Classifier: Operating System :: OS Independent
Requires-Python: >=3.9
License-File: LICENSE
Dynamic: license-file
